delgrada/__init__.py
delgrada/dtype.py
delgrada/scalar.py
delgrada/tensops.py
delgrada/tensor.py
delgrada-0.1.2.dist-info/LICENSE.txt
delgrada-0.1.2.dist-info/METADATA
delgrada-0.1.2.dist-info/WHEEL
delgrada-0.1.2.dist-info/top_level.txt
delgrada-0.1.2.dist-info/RECORD
