Metadata-Version: 2.1
Name: delgrada
Version: 0.1.2
Summary: Lightweight, minimal tensor-/scalar- based autograd engine.
Home-page: https://github.com/perceptronv/delgrada/
Author: Yiding Song
Author-email: perceptronv@gmail.com
Project-URL: Source, https://github.com/perceptronv/delgrada/
Keywords: autograd,deep-learning,mathematics,education
Classifier: Development Status :: 3 - Alpha
Classifier: Intended Audience :: Education
Classifier: Intended Audience :: Developers
Classifier: Topic :: Education
Classifier: Topic :: Scientific/Engineering :: Artificial Intelligence
Classifier: Topic :: Scientific/Engineering :: Mathematics
Classifier: Topic :: Software Development
Classifier: License :: OSI Approved :: MIT License
Classifier: Programming Language :: Python :: 3
Classifier: Operating System :: OS Independent
Requires-Python: >=3.7, <4
License-File: LICENSE.txt
Requires-Dist: numpy
